Metadata-Version: 1.0
Name: dada-sql
Version: 0.0.9
Summary: SQL utilities and views for dada-lake
Home-page: http://globally.ltd
Author: gltd
Author-email: hey@gltd.email
License: UNKNOWN
Platform: UNKNOWN
